Metadata-Version: 1.0
Name: fancy-tag
Version: 0.1.5
Summary: A replacement for Django's simple_tag decorator.
Home-page: https://github.com/trapeze/fancy_tag
Author: Sam Bull
Author-email: sam@pocketuniverse.ca
License: UNKNOWN
Platform: UNKNOWN
Classifier: Programming Language :: Python
Classifier: Framework :: Django
